oread/__init__.py
oread/__main__.py
oread/version.py
Oread-1.1.dist-info/LICENSE
Oread-1.1.dist-info/METADATA
Oread-1.1.dist-info/WHEEL
Oread-1.1.dist-info/top_level.txt
Oread-1.1.dist-info/RECORD
