Metadata-Version: 2.1
Name: Oread
Version: 1.1
Summary: A commandline and GUI tool for the creation of Artemis/Artemis Comparison Tool files.
Home-page: https://github.com/jrjhealey/Oread
Author: Joe R. J. Healey
Author-email: jrj.healey@gmail.com
License: GNU General Public License v3.0
Platform: UNKNOWN
Classifier: Programming Language :: Python :: 2.7
Classifier: Programming Language :: Python :: 3.7
Classifier: Topic :: Scientific/Engineering :: Bio-Informatics
Classifier: Environment :: MacOS X
Classifier: Intended Audience :: Science/Research
Classifier: License :: OSI Approved :: GNU General Public License v3 (GPLv3)
Requires-Dist: biopython
Requires-Dist: gooey
